verloopcontext/__init__.py
verloopcontext/context.py
verloopcontext/header.py
verloopcontext/logging.py
verloopcontext-0.0.5.dist-info/METADATA
verloopcontext-0.0.5.dist-info/WHEEL
verloopcontext-0.0.5.dist-info/top_level.txt
verloopcontext-0.0.5.dist-info/RECORD
